sqlite_generate/__init__.py
sqlite_generate/cli.py
sqlite_generate/utils.py
sqlite_generate-1.1.1.dist-info/LICENSE
sqlite_generate-1.1.1.dist-info/METADATA
sqlite_generate-1.1.1.dist-info/WHEEL
sqlite_generate-1.1.1.dist-info/entry_points.txt
sqlite_generate-1.1.1.dist-info/top_level.txt
sqlite_generate-1.1.1.dist-info/RECORD
