Metadata-Version: 2.1
Name: sqlite-generate
Version: 1.1.1
Summary: Tool for generating demo SQLite databases
Home-page: https://github.com/simonw/sqlite-generate
Author: Simon Willison
License: Apache License, Version 2.0
Project-URL: Issues, https://github.com/simonw/sqlite-generate/issues
Project-URL: CI, https://github.com/simonw/sqlite-generate/actions
Project-URL: Changelog, https://github.com/simonw/sqlite-generate/releases
Platform: UNKNOWN
Requires-Dist: click
Requires-Dist: Faker
Requires-Dist: sqlite-utils
Provides-Extra: test
Requires-Dist: pytest ; extra == 'test'
